Metadata-Version: 2.1
Name: aicore-nb-tools
Version: 0.1.2
Summary: Create a notebook with questions for AiCore students
Home-page: UNKNOWN
Author: Ivan Ying
License: UNKNOWN
Platform: UNKNOWN
